collective.conferences-0.1.dev0-py3.6-nspkg.pth
collective/conferences/__init__.py
collective/conferences/attendee.py
collective/conferences/attendeefolder.py
collective/conferences/callforpaper.py
collective/conferences/common.py
collective/conferences/conference.py
collective/conferences/conferencebreak.py
collective/conferences/conferencespeaker.py
collective/conferences/configure.zcml
collective/conferences/createnewtalk.py
collective/conferences/createnewworkshop.py
collective/conferences/customspeakername.py
collective/conferences/customspeakerurl.py
collective/conferences/indexers.py
collective/conferences/interfaces.py
collective/conferences/permissions.zcml
collective/conferences/program.py
collective/conferences/room.py
collective/conferences/roomfolder.py
collective/conferences/setuphandlers.py
collective/conferences/speakerfolder.py
collective/conferences/talk.py
collective/conferences/talksfolder.py
collective/conferences/testing.py
collective/conferences/track.py
collective/conferences/upgrades.py
collective/conferences/upgrades.zcml
collective/conferences/vocabularies.py
collective/conferences/workshop.py
collective/conferences/workshopfolder.py
collective/conferences/attendee_templates/view.pt
collective/conferences/attendeefolder_templates/view.pt
collective/conferences/browser/.gitkeep
collective/conferences/browser/__init__.py
collective/conferences/browser/configure.zcml
collective/conferences/browser/controlpanel.py
collective/conferences/browser/overrides/gitkeep
collective/conferences/browser/static/gitkeep
collective/conferences/callforpaper_templates/view.pt
collective/conferences/conference_templates/view.pt
collective/conferences/conferencebreak_templates/view.pt
collective/conferences/conferencespeaker_templates/view.pt
collective/conferences/locales/.gitkeep
collective/conferences/locales/README.rst
collective/conferences/locales/__init__.py
collective/conferences/locales/collective.conferences.pot
collective.conferences-0.1.dev0.dist-info/LICENSE.GPL
collective.conferences-0.1.dev0.dist-info/LICENSE.rst
collective.conferences-0.1.dev0.dist-info/METADATA
collective.conferences-0.1.dev0.dist-info/WHEEL
collective.conferences-0.1.dev0.dist-info/entry_points.txt
collective.conferences-0.1.dev0.dist-info/namespace_packages.txt
collective.conferences-0.1.dev0.dist-info/top_level.txt
collective.conferences-0.1.dev0.dist-info/RECORD
