Metadata-Version: 2.1
Name: collective.conferences
Version: 0.1.dev0
Summary: A Conference Management System for Plone
Home-page: http://github.com/collective/collective.conferences
Author: Andreas Mantke
Author-email: maand@gmx.de
License: GPL version 2
Project-URL: PyPI, https://pypi.python.org/pypi/collective.conferences
Project-URL: Source, https://github.com/collective/collective.conferences
Project-URL: Tracker, https://github.com/collective/collective.conferences/issues
Keywords: Python Plone Conference Organisation Tool
Platform: UNKNOWN
Classifier: Environment :: Web Environment
Classifier: Framework :: Plone
Classifier: Framework :: Plone :: Addon
Classifier: Framework :: Plone :: 5.2
Classifier: Programming Language :: Python
Classifier: Programming Language :: Python :: 2.7
Classifier: Programming Language :: Python :: 3.6
Classifier: Programming Language :: Python :: 3.7
Classifier: Operating System :: OS Independent
Classifier: License :: OSI Approved :: GNU General Public License v2 (GPLv2)
Requires-Python: ==2.7, >=3.6
Requires-Dist: setuptools
Requires-Dist: z3c.jbot
Requires-Dist: plone.api (>=1.8.4)
Requires-Dist: plone.restapi
Requires-Dist: plone.app.dexterity
Requires-Dist: Products.validation
Requires-Dist: collective.dexteritytextindexer
Requires-Dist: plone.formwidget.autocomplete
Requires-Dist: plone.formwidget.contenttree
Requires-Dist: plone.formwidget.recaptcha
Requires-Dist: plone.app.z3cform (>=3.2.0)
Provides-Extra: test
Requires-Dist: plone.app.testing ; extra == 'test'
Requires-Dist: plone.testing (>=5.0.0) ; extra == 'test'
Requires-Dist: plone.app.contenttypes ; extra == 'test'
Requires-Dist: plone.app.robotframework[debug] ; extra == 'test'
Requires-Dist: Products.validation ; extra == 'test'
Requires-Dist: plone.formwidget.recaptcha ; extra == 'test'
